Pluxbox_RadioManager_Client-1.1.6.dist-info/DESCRIPTION.rst
Pluxbox_RadioManager_Client-1.1.6.dist-info/METADATA
Pluxbox_RadioManager_Client-1.1.6.dist-info/RECORD
Pluxbox_RadioManager_Client-1.1.6.dist-info/WHEEL
Pluxbox_RadioManager_Client-1.1.6.dist-info/metadata.json
Pluxbox_RadioManager_Client-1.1.6.dist-info/top_level.txt
radiomanager_sdk/__init__.py
radiomanager_sdk/api_client.py
radiomanager_sdk/configuration.py
radiomanager_sdk/rest.py
radiomanager_sdk/apis/__init__.py
radiomanager_sdk/apis/block_api.py
radiomanager_sdk/apis/broadcast_api.py
radiomanager_sdk/apis/campaign_api.py
radiomanager_sdk/apis/contact_api.py
radiomanager_sdk/apis/genre_api.py
radiomanager_sdk/apis/item_api.py
radiomanager_sdk/apis/model_type_api.py
radiomanager_sdk/apis/presenter_api.py
radiomanager_sdk/apis/program_api.py
radiomanager_sdk/apis/station_api.py
radiomanager_sdk/apis/story_api.py
radiomanager_sdk/apis/string_api.py
radiomanager_sdk/apis/tag_api.py
radiomanager_sdk/apis/user_api.py
radiomanager_sdk/apis/visual_slide_api.py
radiomanager_sdk/models/__init__.py
radiomanager_sdk/models/block.py
radiomanager_sdk/models/block_relations.py
radiomanager_sdk/models/block_relations_broadcast.py
radiomanager_sdk/models/block_relations_broadcast_params.py
radiomanager_sdk/models/block_relations_items.py
radiomanager_sdk/models/block_relations_items_params.py
radiomanager_sdk/models/block_relations_program.py
radiomanager_sdk/models/block_result.py
radiomanager_sdk/models/block_results.py
radiomanager_sdk/models/broadcast.py
radiomanager_sdk/models/broadcast_data_input.py
radiomanager_sdk/models/broadcast_epg_day.py
radiomanager_sdk/models/broadcast_epg_relations.py
radiomanager_sdk/models/broadcast_epg_result.py
radiomanager_sdk/models/broadcast_input_only.py
radiomanager_sdk/models/broadcast_output_only.py
radiomanager_sdk/models/broadcast_relations.py
radiomanager_sdk/models/broadcast_relations_blocks.py
radiomanager_sdk/models/broadcast_relations_items.py
radiomanager_sdk/models/broadcast_relations_items_params.py
radiomanager_sdk/models/broadcast_relations_model_type.py
radiomanager_sdk/models/broadcast_relations_presenters.py
radiomanager_sdk/models/broadcast_relations_tags.py
radiomanager_sdk/models/broadcast_result.py
