Metadata-Version: 2.0
Name: Pluxbox-RadioManager-Client
Version: 1.1.6
Summary: RadioManager
Home-page: http://pluxbox.com
Author: UNKNOWN
Author-email: support@pluxbox.com
License: MIT
Keywords: pluxbox,radio,radiomanager,sdk,api,RadioManager
Platform: UNKNOWN
Requires-Dist: certifi
Requires-Dist: python-dateutil
Requires-Dist: six (>=1.10)
Requires-Dist: urllib3 (>=1.15)
